my_project/__init__.py
my_project/main.py
llama_index_collection-0.2.0.dist-info/METADATA
llama_index_collection-0.2.0.dist-info/WHEEL
llama_index_collection-0.2.0.dist-info/RECORD
