Metadata-Version: 2.1
Name: llama-index-collection
Version: 0.2.0
Summary: A streamlined collection of essential LlamaIndex packages for lightweight and efficient usage.
Author: shloimy wiesel
Author-email: w63071@gmail.com
Requires-Python: >=3.10,<3.13
Classifier: Programming Language :: Python :: 3
Classifier: Programming Language :: Python :: 3.10
Classifier: Programming Language :: Python :: 3.11
Classifier: Programming Language :: Python :: 3.12
Requires-Dist: Deprecated (==1.2.15)
Requires-Dist: Jinja2 (==3.1.4)
Requires-Dist: MarkupSafe (==3.0.2)
Requires-Dist: PyYAML (==6.0.2)
Requires-Dist: Pygments (==2.18.0)
Requires-Dist: SQLAlchemy[asyncio] (==2.0.36)
Requires-Dist: aiohappyeyeballs (==2.4.3)
Requires-Dist: aiohttp (==3.11.2)
Requires-Dist: aiosignal (==1.3.1)
Requires-Dist: annotated-types (==0.7.0)
Requires-Dist: anyio (==4.6.2.post1)
Requires-Dist: async-timeout (==5.0.1)
Requires-Dist: attrs (==24.2.0)
Requires-Dist: beautifulsoup4 (==4.12.3)
Requires-Dist: certifi (==2024.8.30)
Requires-Dist: charset-normalizer (==3.4.0)
Requires-Dist: click (==8.1.7)
Requires-Dist: coloredlogs (==15.0.1)
Requires-Dist: dataclasses-json (==0.6.7)
Requires-Dist: dirtyjson (==1.0.8)
Requires-Dist: distro (==1.9.0)
Requires-Dist: dnspython (==2.7.0)
Requires-Dist: email-validator (==2.2.0)
Requires-Dist: exceptiongroup (==1.2.2)
Requires-Dist: fastapi-cli[standard] (==0.0.5)
Requires-Dist: fastapi[standard] (==0.115.5)
Requires-Dist: filelock (==3.16.1)
Requires-Dist: filetype (==1.2.0)
Requires-Dist: flatbuffers (==24.3.25)
Requires-Dist: frozenlist (==1.5.0)
Requires-Dist: fsspec (==2024.10.0)
Requires-Dist: greenlet (==3.1.1)
Requires-Dist: grpcio (==1.68.0)
Requires-Dist: grpcio-tools (==1.68.0)
Requires-Dist: h11 (==0.14.0)
Requires-Dist: h2 (==4.1.0)
Requires-Dist: hpack (==4.0.0)
Requires-Dist: httpcore (==1.0.7)
Requires-Dist: httptools (==0.6.4)
Requires-Dist: httpx[http2] (==0.27.2)
Requires-Dist: huggingface-hub[inference] (==0.26.2)
Requires-Dist: humanfriendly (==10.0)
Requires-Dist: hyperframe (==6.0.1)
Requires-Dist: idna (==3.10)
Requires-Dist: iniconfig (==2.0.0)
Requires-Dist: jiter (==0.7.1)
Requires-Dist: joblib (==1.4.2)
Requires-Dist: ldap3 (==2.9.1)
Requires-Dist: llama-cloud (==0.1.6)
Requires-Dist: llama-index (==0.12.0)
Requires-Dist: llama-index-agent-openai (==0.4.0)
Requires-Dist: llama-index-cli (==0.4.0)
Requires-Dist: llama-index-core (==0.12.0)
Requires-Dist: llama-index-embeddings-huggingface (==0.4.0)
Requires-Dist: llama-index-embeddings-openai (==0.3.1)
Requires-Dist: llama-index-indices-managed-llama-cloud (==0.6.3)
Requires-Dist: llama-index-legacy (==0.9.48.post4)
Requires-Dist: llama-index-llms-openai (==0.3.0)
Requires-Dist: llama-index-llms-openai-like (==0.3.0)
Requires-Dist: llama-index-llms-text-generation-inference (==0.3.0)
Requires-Dist: llama-index-multi-modal-llms-openai (==0.3.0)
Requires-Dist: llama-index-program-openai (==0.3.1)
Requires-Dist: llama-index-question-gen-openai (==0.3.0)
Requires-Dist: llama-index-readers-file (==0.4.0)
Requires-Dist: llama-index-readers-llama-parse (==0.4.0)
Requires-Dist: llama-index-utils-huggingface (==0.3.0)
Requires-Dist: llama-index-vector-stores-qdrant (==0.4.0)
Requires-Dist: llama-parse (==0.5.17)
Requires-Dist: loguru (==0.7.2)
Requires-Dist: markdown-it-py (==3.0.0)
Requires-Dist: marshmallow (==3.23.1)
Requires-Dist: mdurl (==0.1.2)
Requires-Dist: mmh3 (==4.1.0)
Requires-Dist: mpmath (==1.3.0)
Requires-Dist: multidict (==6.1.0)
Requires-Dist: mypy-extensions (==1.0.0)
Requires-Dist: nest-asyncio (==1.6.0)
Requires-Dist: networkx (==3.4.2)
Requires-Dist: nltk (==3.9.1)
Requires-Dist: numpy (==2.1.3)
Requires-Dist: nvidia-cublas-cu12 (==12.4.5.8)
Requires-Dist: nvidia-cuda-cupti-cu12 (==12.4.127)
Requires-Dist: nvidia-cuda-nvrtc-cu12 (==12.4.127)
Requires-Dist: nvidia-cuda-runtime-cu12 (==12.4.127)
Requires-Dist: nvidia-cudnn-cu12 (==9.1.0.70)
Requires-Dist: nvidia-cufft-cu12 (==11.2.1.3)
Requires-Dist: nvidia-curand-cu12 (==10.3.5.147)
Requires-Dist: nvidia-cusolver-cu12 (==11.6.1.9)
Requires-Dist: nvidia-cusparse-cu12 (==12.3.1.170)
Requires-Dist: nvidia-nccl-cu12 (==2.21.5)
Requires-Dist: nvidia-nvjitlink-cu12 (==12.4.127)
Requires-Dist: nvidia-nvtx-cu12 (==12.4.127)
Requires-Dist: onnx (==1.17.0)
Requires-Dist: onnxruntime (==1.19.2)
Requires-Dist: openai (==1.54.4)
Requires-Dist: packaging (==24.2)
Requires-Dist: pandas (==2.2.3)
Requires-Dist: pillow (==10.4.0)
Requires-Dist: pluggy (==1.5.0)
Requires-Dist: portalocker (==2.10.1)
Requires-Dist: propcache (==0.2.0)
Requires-Dist: protobuf (==5.28.3)
Requires-Dist: py-rust-stemmers (==0.1.3)
Requires-Dist: pyasn1 (==0.6.1)
Requires-Dist: pydantic (==2.9.2)
Requires-Dist: pydantic-core (==2.23.4)
Requires-Dist: pydantic-settings (==2.6.1)
Requires-Dist: pymongo (==4.10.1)
Requires-Dist: pymupdf (==1.25.0)
Requires-Dist: pymupdf4llm (==0.0.17)
Requires-Dist: pypdf (==5.1.0)
Requires-Dist: pytest (==8.3.4)
Requires-Dist: pytest-asyncio (==0.24.0)
Requires-Dist: python-dateutil (==2.9.0.post0)
Requires-Dist: python-dotenv (==1.0.1)
Requires-Dist: python-multipart (==0.0.17)
Requires-Dist: pytz (==2024.2)
Requires-Dist: qdrant-client (==1.12.1)
Requires-Dist: redis (==5.2.0)
Requires-Dist: regex (==2024.11.6)
Requires-Dist: requests (==2.32.3)
Requires-Dist: rich (==13.9.4)
Requires-Dist: safetensors (==0.4.5)
Requires-Dist: scikit-learn (==1.5.2)
Requires-Dist: scipy (==1.14.1)
Requires-Dist: sentence-transformers (==3.0.0)
Requires-Dist: shellingham (==1.5.4)
Requires-Dist: six (==1.16.0)
Requires-Dist: sniffio (==1.3.1)
Requires-Dist: soupsieve (==2.6)
Requires-Dist: starlette (==0.41.2)
Requires-Dist: striprtf (==0.0.26)
Requires-Dist: sympy (==1.13.1)
Requires-Dist: tenacity (==8.5.0)
Requires-Dist: termcolor (==2.5.0)
Requires-Dist: text-generation (==0.7.0)
Requires-Dist: threadpoolctl (==3.5.0)
Requires-Dist: tiktoken (==0.8.0)
Requires-Dist: tokenizers (==0.20.3)
Requires-Dist: tomli (==2.2.1)
Requires-Dist: torch (==2.5.1)
Requires-Dist: tqdm (==4.67.0)
Requires-Dist: transformers (==4.46.2)
Requires-Dist: triton (==3.1.0)
Requires-Dist: typer (==0.13.0)
Requires-Dist: typing-extensions (==4.12.2)
Requires-Dist: typing-inspect (==0.9.0)
Requires-Dist: tzdata (==2024.2)
Requires-Dist: urllib3 (==2.2.3)
Requires-Dist: uvicorn[standard] (==0.32.0)
Requires-Dist: uvloop (==0.21.0)
Requires-Dist: watchfiles (==0.24.0)
Requires-Dist: websockets (==14.1)
Requires-Dist: wrapt (==1.16.0)
Requires-Dist: yarl (==1.17.2)
